[{"Code":"1105082001","Parent":"1105082","Name":"ARUL PINANG","Latitude":"","Longitude":"","Postal":"24462,24461"},{"Code":"1105082002","Parent":"1105082","Name":"PEUNARON BARU","Latitude":"","Longitude":"","Postal":"24462,24461"},{"Code":"1105082003","Parent":"1105082","Name":"PEUNARON LAMA","Latitude":"","Longitude":"","Postal":"24462,24461"},{"Code":"1105082004","Parent":"1105082","Name":"BUKIT TIGA","Latitude":"","Longitude":"","Postal":"24462,24461"},{"Code":"1105082006","Parent":"1105082","Name":"SRI MULYA","Latitude":"","Longitude":"","Postal":"24462,24461"}]