[{"Code":"1110060001","Parent":"1110060","Name":"ABEUK USONG","Latitude":"","Longitude":"","Postal":"24269,24251"},{"Code":"1110060002","Parent":"1110060","Name":"BLANG SEUPENG","Latitude":"","Longitude":"","Postal":"24269,24251"},{"Code":"1110060003","Parent":"1110060","Name":"COT IBOEH","Latitude":"","Longitude":"","Postal":"24269,24251"},{"Code":"1110060004","Parent":"1110060","Name":"SEUNEUBOK LHONG","Latitude":"","Longitude":"","Postal":"24269,24251"},{"Code":"1110060005","Parent":"1110060","Name":"PALOH PANYANG","Latitude":"","Longitude":"","Postal":"24269,24251"},{"Code":"1110060006","Parent":"1110060","Name":"BLANG RHEUM","Latitude":"","Longitude":"","Postal":"24269,24251"},{"Code":"1110060007","Parent":"1110060","Name":"COT ULIM","Latitude":"","Longitude":"","Postal":"24269,24251"},{"Code":"1110060008","Parent":"1110060","Name":"COT LEUSONG","Latitude":"","Longitude":"","Postal":"24269,24251"},{"Code":"1110060009","Parent":"1110060","Name":"BLANG SEUNONG","Latitude":"","Longitude":"","Postal":"24269,24251"},{"Code":"1110060010","Parent":"1110060","Name":"COT KEUTAPANG","Latitude":"","Longitude":"","Postal":"24262,24269,24251"},{"Code":"1110060027","Parent":"1110060","Name":"COT TAROM TUNONG","Latitude":"","Longitude":"","Postal":"24269,24251"},{"Code":"1110060028","Parent":"1110060","Name":"BLANG COT TUNONG","Latitude":"","Longitude":"","Postal":"24269,24251"},{"Code":"1110060029","Parent":"1110060","Name":"SEULEUMBAH","Latitude":"","Longitude":"","Postal":"24269,24251"},{"Code":"1110060030","Parent":"1110060","Name":"ABEUK TINGKEUM","Latitude":"","Longitude":"","Postal":"24269,24251"},{"Code":"1110060031","Parent":"1110060","Name":"BLANG ME","Latitude":"","Longitude":"","Postal":"24269,24251"},{"Code":"1110060032","Parent":"1110060","Name":"PULO LAWANG","Latitude":"","Longitude":"","Postal":"24262,24269,24251"},{"Code":"1110060033","Parent":"1110060","Name":"PALOH SEULIMENG","Latitude":"","Longitude":"","Postal":"24269,24251"},{"Code":"1110060034","Parent":"1110060","Name":"TEUPOK TUNONG","Latitude":"","Longitude":"","Postal":"24269,24251"},{"Code":"1110060035","Parent":"1110060","Name":"TEUPOK BAROH","Latitude":"","Longitude":"","Postal":"24269,24251"},{"Code":"1110060036","Parent":"1110060","Name":"COT BADA","Latitude":"","Longitude":"","Postal":"24269,24251"},{"Code":"1110060037","Parent":"1110060","Name":"COT GADONG","Latitude":"","Longitude":"","Postal":"24269,24251"},{"Code":"1110060038","Parent":"1110060","Name":"KUALA JEUMPA","Latitude":"","Longitude":"","Postal":"24269,24251"},{"Code":"1110060039","Parent":"1110060","Name":"BLANG DALAM","Latitude":"","Longitude":"","Postal":"24261,24269,24251"},{"Code":"1110060040","Parent":"1110060","Name":"BLANG BLADEH","Latitude":"","Longitude":"","Postal":"24269,24251"},{"Code":"1110060041","Parent":"1110060","Name":"GEULUMPANG PAYONG","Latitude":"","Longitude":"","Postal":"24264,24251"},{"Code":"1110060042","Parent":"1110060","Name":"BLANG COT BAROH","Latitude":"","Longitude":"","Postal":"24269,24251"},{"Code":"1110060043","Parent":"1110060","Name":"COT TAROM BAROH","Latitude":"","Longitude":"","Postal":"24269,24251"},{"Code":"1110060044","Parent":"1110060","Name":"GEUDONG TAMPU","Latitude":"","Longitude":"","Postal":"24269,24251"},{"Code":"1110060061","Parent":"1110060","Name":"LIPAH CUT","Latitude":"","Longitude":"","Postal":"24269,24251"},{"Code":"1110060062","Parent":"1110060","Name":"LIPAH RAYEUK","Latitude":"","Longitude":"","Postal":"24269,24251"},{"Code":"1110060063","Parent":"1110060","Name":"MON JAMBEE","Latitude":"","Longitude":"","Postal":"24269,24251"},{"Code":"1110060064","Parent":"1110060","Name":"BATEE TIMOH","Latitude":"","Longitude":"","Postal":"24269,24251"},{"Code":"1110060065","Parent":"1110060","Name":"COT GEURUNDONG","Latitude":"","Longitude":"","Postal":"24269,24251"},{"Code":"1110060066","Parent":"1110060","Name":"BEURAWANG","Latitude":"","Longitude":"","Postal":"24269,24251"},{"Code":"1110060073","Parent":"1110060","Name":"BLANG GANDAI","Latitude":"","Longitude":"","Postal":"24269,24251"},{"Code":"1110060075","Parent":"1110060","Name":"SALAH SIRONG JAYA","Latitude":"","Longitude":"","Postal":"24269,24251"},{"Code":"1110060076","Parent":"1110060","Name":"MON MANE","Latitude":"","Longitude":"","Postal":"24269,24251"},{"Code":"1110060077","Parent":"1110060","Name":"ALUE LIMENG","Latitude":"","Longitude":"","Postal":"24269,24251"},{"Code":"1110060078","Parent":"1110060","Name":"COT MEUGOE","Latitude":"","Longitude":"","Postal":"24269,24251"},{"Code":"1110060079","Parent":"1110060","Name":"COT IBOEH TIMU","Latitude":"","Longitude":"","Postal":"24269,24251"},{"Code":"1110060080","Parent":"1110060","Name":"KUTA MEULIGOE","Latitude":"","Longitude":"","Postal":"24269,24251"},{"Code":"1110060081","Parent":"1110060","Name":"LHAKSMANA","Latitude":"","Longitude":"","Postal":"24251"}]