[{"Code":"1113041001","Parent":"1113041","Name":"TETINGI","Latitude":"","Longitude":"","Postal":"24659,24654"},{"Code":"1113041002","Parent":"1113041","Name":"REMUKUT","Latitude":"","Longitude":"","Postal":"24659,24654"},{"Code":"1113041003","Parent":"1113041","Name":"SENEREN","Latitude":"","Longitude":"","Postal":"24654"},{"Code":"1113041004","Parent":"1113041","Name":"KENYARAN","Latitude":"","Longitude":"","Postal":"24659,24654"},{"Code":"1113041005","Parent":"1113041","Name":"ATU KAPUR","Latitude":"","Longitude":"","Postal":"24659,24654"},{"Code":"1113041006","Parent":"1113041","Name":"UNING KURNIA","Latitude":"","Longitude":"","Postal":"24659,24654"},{"Code":"1113041007","Parent":"1113041","Name":"SURI MUSARA","Latitude":"","Longitude":"","Postal":"24659,24654"},{"Code":"1113041008","Parent":"1113041","Name":"CANE BARU","Latitude":"","Longitude":"","Postal":"24659,24654"},{"Code":"1113041009","Parent":"1113041","Name":"AIH SELAH","Latitude":"","Longitude":"","Postal":""}]