[{"Code":"1209010002","Parent":"1209010","Name":"SIBANGUN MERIAH","Latitude":"","Longitude":"","Postal":"21169"},{"Code":"1209010004","Parent":"1209010","Name":"SARIBU DOLOK","Latitude":"","Longitude":"","Postal":"21167,21169"},{"Code":"1209010005","Parent":"1209010","Name":"PURBA SINOMBAH","Latitude":"","Longitude":"","Postal":"21167,21169"},{"Code":"1209010006","Parent":"1209010","Name":"PURBA TUA","Latitude":"","Longitude":"","Postal":"21167,21169"},{"Code":"1209010011","Parent":"1209010","Name":"PURBA TUA BARU","Latitude":"","Longitude":"","Postal":"21167,21169"},{"Code":"1209010014","Parent":"1209010","Name":"SINAR BARU","Latitude":"","Longitude":"","Postal":"21167,21169"},{"Code":"1209010015","Parent":"1209010","Name":"PURBA TUA ETEK","Latitude":"","Longitude":"","Postal":"21167,21169"}]