[{"Code":"1209050001","Parent":"1209050","Name":"SIPANGAN BOLON","Latitude":"","Longitude":"","Postal":"21174"},{"Code":"1209050002","Parent":"1209050","Name":"GIRSANG","Latitude":"","Longitude":"","Postal":"21174"},{"Code":"1209050003","Parent":"1209050","Name":"PARAPAT","Latitude":"","Longitude":"","Postal":"21174"},{"Code":"1209050004","Parent":"1209050","Name":"TIGA RAJA","Latitude":"","Longitude":"","Postal":"21174"},{"Code":"1209050005","Parent":"1209050","Name":"SIBAGANDING","Latitude":"","Longitude":"","Postal":"21174"},{"Code":"1209050006","Parent":"1209050","Name":"SIPANGAN BOLON MEKAR","Latitude":"","Longitude":"","Postal":"21174"}]