[{"Code":"1402030015","Parent":"1402030","Name":"PULAU SENGKILO","Latitude":"","Longitude":"","Postal":"29357,29352"},{"Code":"1402030016","Parent":"1402030","Name":"KOTA MEDAN","Latitude":"","Longitude":"","Postal":"29357,29352"},{"Code":"1402030017","Parent":"1402030","Name":"POLAK PISANG","Latitude":"","Longitude":"","Postal":"29357,29352"},{"Code":"1402030018","Parent":"1402030","Name":"SIMPANG KOTA MEDAN","Latitude":"","Longitude":"","Postal":"29357,29352"},{"Code":"1402030019","Parent":"1402030","Name":"TANJUNG BELUDU","Latitude":"","Longitude":"","Postal":"29357,29352"},{"Code":"1402030020","Parent":"1402030","Name":"PELANGKO","Latitude":"","Longitude":"","Postal":"29357,29352"},{"Code":"1402030021","Parent":"1402030","Name":"SIMPANG KELAYANG","Latitude":"","Longitude":"","Postal":"29357,29352"},{"Code":"1402030022","Parent":"1402030","Name":"TELUK SEJUAH","Latitude":"","Longitude":"","Postal":"29357,29352"},{"Code":"1402030023","Parent":"1402030","Name":"DUSUN TUA","Latitude":"","Longitude":"","Postal":"29357,29352"},{"Code":"1402030024","Parent":"1402030","Name":"BONGKAL MALANG","Latitude":"","Longitude":"","Postal":"29357,29352"},{"Code":"1402030025","Parent":"1402030","Name":"SUNGAI BANYAK IKAN","Latitude":"","Longitude":"","Postal":"29357,29352"},{"Code":"1402030026","Parent":"1402030","Name":"SUNGAI PASIR PUTIH","Latitude":"","Longitude":"","Postal":"29357,29352"},{"Code":"1402030027","Parent":"1402030","Name":"SUNGAI GOLANG","Latitude":"","Longitude":"","Postal":"29357,29352"},{"Code":"1402030028","Parent":"1402030","Name":"SUNGAI KUNING BENIO","Latitude":"","Longitude":"","Postal":"29357,29352"},{"Code":"1402030029","Parent":"1402030","Name":"PASIR BERINGIN","Latitude":"","Longitude":"","Postal":"29357,29352"},{"Code":"1402030030","Parent":"1402030","Name":"BUKIT SELANJUT","Latitude":"","Longitude":"","Postal":"29357,29352"},{"Code":"1402030031","Parent":"1402030","Name":"DUSUN TUA PELANG","Latitude":"","Longitude":"","Postal":"29357,29352"}]