[{"Code":"1405024001","Parent":"1405024","Name":"EMPANG BARU","Latitude":"","Longitude":"","Postal":"28654,28655"},{"Code":"1405024002","Parent":"1405024","Name":"SIALANG PALAS","Latitude":"","Longitude":"","Postal":"28654,28655"},{"Code":"1405024003","Parent":"1405024","Name":"SIALANG BARU","Latitude":"","Longitude":"","Postal":"28654,28655"},{"Code":"1405024004","Parent":"1405024","Name":"LUBUK DALAM","Latitude":"","Longitude":"","Postal":"28654,28655"},{"Code":"1405024005","Parent":"1405024","Name":"RAWANG KAO","Latitude":"","Longitude":"","Postal":"28654,28655"},{"Code":"1405024006","Parent":"1405024","Name":"SRI GADING","Latitude":"","Longitude":"","Postal":"28654,28655"},{"Code":"1405024007","Parent":"1405024","Name":"RAWANG KAO BARAT","Latitude":"","Longitude":"","Postal":"28654,28655"}]