[{"Code":"1502022001","Parent":"1502022","Name":"SEKANCING","Latitude":"","Longitude":"","Postal":"37375,37371"},{"Code":"1502022002","Parent":"1502022","Name":"BERINGIN SANGGUL","Latitude":"","Longitude":"","Postal":"37375,37371"},{"Code":"1502022003","Parent":"1502022","Name":"RANTAU LIMAU KAPAS","Latitude":"","Longitude":"","Postal":"37375,37353"},{"Code":"1502022004","Parent":"1502022","Name":"SEKANCING ILIR","Latitude":"","Longitude":"","Postal":"37375,37371"},{"Code":"1502022005","Parent":"1502022","Name":"BARU BUKIT PUNJUNG","Latitude":"","Longitude":"","Postal":"37371"},{"Code":"1502022006","Parent":"1502022","Name":"BARU SUNGAI SAKAI","Latitude":"","Longitude":"","Postal":"37371"}]