[{"Code":"1707010001","Parent":"1707010","Name":"BIOA SENGOK","Latitude":"","Longitude":"","Postal":"39261"},{"Code":"1707010002","Parent":"1707010","Name":"RIMBO PENGADANG","Latitude":"","Longitude":"","Postal":"39261"},{"Code":"1707010003","Parent":"1707010","Name":"TELUK DIEN","Latitude":"","Longitude":"","Postal":"39261"},{"Code":"1707010009","Parent":"1707010","Name":"TALANG RATU","Latitude":"","Longitude":"","Postal":"39261"},{"Code":"1707010011","Parent":"1707010","Name":"TIK KUTO","Latitude":"","Longitude":"","Postal":"39261"},{"Code":"1707010012","Parent":"1707010","Name":"BAJOK","Latitude":"","Longitude":"","Postal":"39261"}]