[{"Code":"1805080006","Parent":"1805080","Name":"ADI JAYA","Latitude":"","Longitude":"","Postal":"34263,34163"},{"Code":"1805080008","Parent":"1805080","Name":"YUKUM JAYA","Latitude":"","Longitude":"","Postal":"34263,34163"},{"Code":"1805080009","Parent":"1805080","Name":"INDRA PUTRA SUBING","Latitude":"","Longitude":"","Postal":"34263,34163"},{"Code":"1805080010","Parent":"1805080","Name":"KARANG ENDAH","Latitude":"","Longitude":"","Postal":"34263,34163"},{"Code":"1805080011","Parent":"1805080","Name":"NAMBAH DADI","Latitude":"","Longitude":"","Postal":"34263,34163"},{"Code":"1805080012","Parent":"1805080","Name":"ONO HARJO","Latitude":"","Longitude":"","Postal":"34263,34163"},{"Code":"1805080013","Parent":"1805080","Name":"TERBANGGI BESAR","Latitude":"","Longitude":"","Postal":"34263,34269,34163"},{"Code":"1805080015","Parent":"1805080","Name":"BANDAR JAYA TIMUR","Latitude":"","Longitude":"","Postal":"34263,34163"},{"Code":"1805080016","Parent":"1805080","Name":"BANDAR JAYA BARAT","Latitude":"","Longitude":"","Postal":"34263,34163"}]