[{"Code":"2103043001","Parent":"2103043","Name":"SEDEDAP","Latitude":"","Longitude":"","Postal":"29753,29788"},{"Code":"2103043002","Parent":"2103043","Name":"SABANG MAWANG","Latitude":"","Longitude":"","Postal":"29753,29788"},{"Code":"2103043004","Parent":"2103043","Name":"TANJUNG BATANG","Latitude":"","Longitude":"","Postal":"29753,29788"},{"Code":"2103043005","Parent":"2103043","Name":"SERANTAS","Latitude":"","Longitude":"","Postal":"29753,29788"},{"Code":"2103043006","Parent":"2103043","Name":"SABANG MAWANG BARAT","Latitude":"","Longitude":"","Postal":"29753,29788"},{"Code":"2103043010","Parent":"2103043","Name":"TELUK LABUH","Latitude":"","Longitude":"","Postal":"29753,29788"}]