[{"Code":"3202240001","Parent":"3202240","Name":"PONDOK KASO TENGAH","Latitude":"","Longitude":"","Postal":"43358"},{"Code":"3202240002","Parent":"3202240","Name":"PASIRDOTON","Latitude":"","Longitude":"","Postal":"43358"},{"Code":"3202240003","Parent":"3202240","Name":"PONDOK KASO TONGGOH","Latitude":"","Longitude":"","Postal":"43358"},{"Code":"3202240004","Parent":"3202240","Name":"BABAKAN PARI","Latitude":"","Longitude":"","Postal":"43358"},{"Code":"3202240005","Parent":"3202240","Name":"TANGKIL","Latitude":"","Longitude":"","Postal":"43358"},{"Code":"3202240006","Parent":"3202240","Name":"JAYABAKTI","Latitude":"","Longitude":"","Postal":"43358"},{"Code":"3202240007","Parent":"3202240","Name":"CIDAHU","Latitude":"","Longitude":"","Postal":"43358"},{"Code":"3202240008","Parent":"3202240","Name":"GIRIJAYA","Latitude":"","Longitude":"","Postal":"43356,43358"}]