[{"Code":"3274040001","Parent":"3274040","Name":"KARYAMULYA","Latitude":"","Longitude":"","Postal":"45135,45131"},{"Code":"3274040002","Parent":"3274040","Name":"SUNYARAGI","Latitude":"","Longitude":"","Postal":"45132"},{"Code":"3274040003","Parent":"3274040","Name":"DRAJAT","Latitude":"","Longitude":"","Postal":"45133"},{"Code":"3274040004","Parent":"3274040","Name":"KESAMBI","Latitude":"","Longitude":"","Postal":"45134"},{"Code":"3274040005","Parent":"3274040","Name":"PEKIRINGAN","Latitude":"","Longitude":"","Postal":"45131"}]