[{"Code":"3312230001","Parent":"3312230","Name":"GIRIYOSO","Latitude":"","Longitude":"","Postal":"57693"},{"Code":"3312230002","Parent":"3312230","Name":"KOPEN","Latitude":"","Longitude":"","Postal":"57693"},{"Code":"3312230003","Parent":"3312230","Name":"JATIPURNO","Latitude":"","Longitude":"","Postal":"57693"},{"Code":"3312230004","Parent":"3312230","Name":"TAWANGREJO","Latitude":"","Longitude":"","Postal":"57693"},{"Code":"3312230005","Parent":"3312230","Name":"JATIPURWO","Latitude":"","Longitude":"","Postal":"57693"},{"Code":"3312230006","Parent":"3312230","Name":"SLOGORETNO","Latitude":"","Longitude":"","Postal":"57693"},{"Code":"3312230007","Parent":"3312230","Name":"KEMBANG","Latitude":"","Longitude":"","Postal":"57693"},{"Code":"3312230008","Parent":"3312230","Name":"GIRIMULYO","Latitude":"","Longitude":"","Postal":"57693"},{"Code":"3312230009","Parent":"3312230","Name":"BALEPANJANG","Latitude":"","Longitude":"","Postal":"57693"},{"Code":"3312230010","Parent":"3312230","Name":"JEPORO","Latitude":"","Longitude":"","Postal":"57693"},{"Code":"3312230011","Parent":"3312230","Name":"MANGUNHARJO","Latitude":"","Longitude":"","Postal":"57693"}]