[{"Code":"3315190001","Parent":"3315190","Name":"RINGINPITU","Latitude":"","Longitude":"","Postal":"58166"},{"Code":"3315190002","Parent":"3315190","Name":"MRISI","Latitude":"","Longitude":"","Postal":"58166"},{"Code":"3315190003","Parent":"3315190","Name":"NGAMBAKREJO","Latitude":"","Longitude":"","Postal":"58166"},{"Code":"3315190004","Parent":"3315190","Name":"KAPUNG","Latitude":"","Longitude":"","Postal":"58166"},{"Code":"3315190005","Parent":"3315190","Name":"KALIWENANG","Latitude":"","Longitude":"","Postal":"58166"},{"Code":"3315190006","Parent":"3315190","Name":"SUGIHMANIK","Latitude":"","Longitude":"","Postal":"58166"},{"Code":"3315190007","Parent":"3315190","Name":"TANGGUNGHARJO","Latitude":"","Longitude":"","Postal":"58166"},{"Code":"3315190008","Parent":"3315190","Name":"BRABO","Latitude":"","Longitude":"","Postal":"58166"},{"Code":"3315190009","Parent":"3315190","Name":"PADANG","Latitude":"","Longitude":"","Postal":"58166"}]