[{"Code":"3519100001","Parent":"3519100","Name":"BLABAKAN","Latitude":"","Longitude":"","Postal":"63153"},{"Code":"3519100002","Parent":"3519100","Name":"WONOREJO","Latitude":"","Longitude":"","Postal":"63153"},{"Code":"3519100003","Parent":"3519100","Name":"KEBONAGUNG","Latitude":"","Longitude":"","Postal":"63152,63153"},{"Code":"3519100004","Parent":"3519100","Name":"DARMOREJO","Latitude":"","Longitude":"","Postal":"63153"},{"Code":"3519100005","Parent":"3519100","Name":"KALIGUNTING","Latitude":"","Longitude":"","Postal":"63153"},{"Code":"3519100006","Parent":"3519100","Name":"SIDODADI","Latitude":"","Longitude":"","Postal":"63153,63112"},{"Code":"3519100007","Parent":"3519100","Name":"KUNCEN","Latitude":"","Longitude":"","Postal":"63153"},{"Code":"3519100008","Parent":"3519100","Name":"KLECOREJO","Latitude":"","Longitude":"","Postal":"63153"},{"Code":"3519100009","Parent":"3519100","Name":"KALIABU","Latitude":"","Longitude":"","Postal":"63153"},{"Code":"3519100010","Parent":"3519100","Name":"KRAJAN","Latitude":"","Longitude":"","Postal":"63153"},{"Code":"3519100011","Parent":"3519100","Name":"PANDEYAN","Latitude":"","Longitude":"","Postal":"63153"},{"Code":"3519100012","Parent":"3519100","Name":"MEJAYAN","Latitude":"","Longitude":"","Postal":"63153"},{"Code":"3519100013","Parent":"3519100","Name":"BANGUNSARI","Latitude":"","Longitude":"","Postal":"63153"},{"Code":"3519100014","Parent":"3519100","Name":"NGAMPEL","Latitude":"","Longitude":"","Postal":"63153"}]