[{"Code":"3525140001","Parent":"3525140","Name":"SAWO","Latitude":"","Longitude":"","Postal":"61155"},{"Code":"3525140002","Parent":"3525140","Name":"KARANGCANGKRING","Latitude":"","Longitude":"","Postal":"61155"},{"Code":"3525140003","Parent":"3525140","Name":"GEDONGKEDOAN","Latitude":"","Longitude":"","Postal":"61155"},{"Code":"3525140004","Parent":"3525140","Name":"BULANGAN","Latitude":"","Longitude":"","Postal":"61155"},{"Code":"3525140005","Parent":"3525140","Name":"WONOKERTO","Latitude":"","Longitude":"","Postal":"61155"},{"Code":"3525140006","Parent":"3525140","Name":"BANGERAN","Latitude":"","Longitude":"","Postal":"61155"},{"Code":"3525140007","Parent":"3525140","Name":"TIREMENGGAL","Latitude":"","Longitude":"","Postal":"61155"},{"Code":"3525140008","Parent":"3525140","Name":"LOWAYU","Latitude":"","Longitude":"","Postal":"61155"},{"Code":"3525140009","Parent":"3525140","Name":"PETIYIN TUNGGAL","Latitude":"","Longitude":"","Postal":"61155"},{"Code":"3525140010","Parent":"3525140","Name":"TEBUWUNG","Latitude":"","Longitude":"","Postal":"61155"},{"Code":"3525140011","Parent":"3525140","Name":"DUKUH KEMBAR","Latitude":"","Longitude":"","Postal":"61155"},{"Code":"3525140012","Parent":"3525140","Name":"MADUMULYOREJO","Latitude":"","Longitude":"","Postal":"61155"},{"Code":"3525140013","Parent":"3525140","Name":"MENTARAS","Latitude":"","Longitude":"","Postal":"61155"},{"Code":"3525140014","Parent":"3525140","Name":"MOJOPETUNG","Latitude":"","Longitude":"","Postal":"61155"},{"Code":"3525140015","Parent":"3525140","Name":"BARON","Latitude":"","Longitude":"","Postal":"61155"},{"Code":"3525140016","Parent":"3525140","Name":"JREBENG","Latitude":"","Longitude":"","Postal":"61155"},{"Code":"3525140017","Parent":"3525140","Name":"IMA AN","Latitude":"","Longitude":"","Postal":"61155"},{"Code":"3525140018","Parent":"3525140","Name":"SEKARGADUNG","Latitude":"","Longitude":"","Postal":"61155"},{"Code":"3525140019","Parent":"3525140","Name":"BABAKBAWO","Latitude":"","Longitude":"","Postal":"61155"},{"Code":"3525140020","Parent":"3525140","Name":"BABAKSARI","Latitude":"","Longitude":"","Postal":"61155"},{"Code":"3525140021","Parent":"3525140","Name":"SAMBOGUNUNG","Latitude":"","Longitude":"","Postal":"61155"},{"Code":"3525140022","Parent":"3525140","Name":"KALIREJO","Latitude":"","Longitude":"","Postal":"61155"},{"Code":"3525140023","Parent":"3525140","Name":"SEMBUNGAN KIDUL","Latitude":"","Longitude":"","Postal":"61155"},{"Code":"3525140024","Parent":"3525140","Name":"SEMBUNG ANYAR","Latitude":"","Longitude":"","Postal":"61155"},{"Code":"3525140025","Parent":"3525140","Name":"DUKUNANYAR","Latitude":"","Longitude":"","Postal":"61155"},{"Code":"3525140026","Parent":"3525140","Name":"PADANG BANDUNG","Latitude":"","Longitude":"","Postal":"61155"}]