[{"Code":"3578190001","Parent":"3578190","Name":"EMBONG KALIASIN","Latitude":"","Longitude":"","Postal":"60271"},{"Code":"3578190002","Parent":"3578190","Name":"KETABANG","Latitude":"","Longitude":"","Postal":"60272"},{"Code":"3578190003","Parent":"3578190","Name":"GENTENG","Latitude":"","Longitude":"","Postal":"60275"},{"Code":"3578190004","Parent":"3578190","Name":"PENELEH","Latitude":"","Longitude":"","Postal":"60274"},{"Code":"3578190005","Parent":"3578190","Name":"KAPASARI","Latitude":"","Longitude":"","Postal":"60273"}]