[{"Code":"3601020001","Parent":"3601020","Name":"RANCAPINANG","Latitude":"","Longitude":"","Postal":"42284"},{"Code":"3601020002","Parent":"3601020","Name":"CIBADAK","Latitude":"","Longitude":"","Postal":"42284"},{"Code":"3601020003","Parent":"3601020","Name":"BATUHIDEUNG","Latitude":"","Longitude":"","Postal":"42284"},{"Code":"3601020004","Parent":"3601020","Name":"TUGU","Latitude":"","Longitude":"","Postal":"42284"},{"Code":"3601020005","Parent":"3601020","Name":"KRAMATJAYA","Latitude":"","Longitude":"","Postal":"42284"},{"Code":"3601020006","Parent":"3601020","Name":"MANGKUALAM","Latitude":"","Longitude":"","Postal":"42284"},{"Code":"3601020007","Parent":"3601020","Name":"PADASUKA","Latitude":"","Longitude":"","Postal":"42284"},{"Code":"3601020008","Parent":"3601020","Name":"CIBURIAL","Latitude":"","Longitude":"","Postal":"42284"},{"Code":"3601020009","Parent":"3601020","Name":"WARINGINKURUNG","Latitude":"","Longitude":"","Postal":"42284"},{"Code":"3601020010","Parent":"3601020","Name":"CIJARALANG","Latitude":"","Longitude":"","Postal":"42284"},{"Code":"3601020011","Parent":"3601020","Name":"CIMANGGU","Latitude":"","Longitude":"","Postal":"42284"},{"Code":"3601020012","Parent":"3601020","Name":"TANGKILSARI","Latitude":"","Longitude":"","Postal":"42284"}]