[{"Code":"5313110001","Parent":"5313110","Name":"GOLO DUKAL","Latitude":"","Longitude":"","Postal":"86515"},{"Code":"5313110002","Parent":"5313110","Name":"PAU","Latitude":"","Longitude":"","Postal":"86516"},{"Code":"5313110003","Parent":"5313110","Name":"WASO","Latitude":"","Longitude":"","Postal":"86517"},{"Code":"5313110004","Parent":"5313110","Name":"WATU","Latitude":"","Longitude":"","Postal":"86511"},{"Code":"5313110005","Parent":"5313110","Name":"TENDA","Latitude":"","Longitude":"","Postal":"86518"},{"Code":"5313110006","Parent":"5313110","Name":"CAREP","Latitude":"","Longitude":"","Postal":"86519"},{"Code":"5313110007","Parent":"5313110","Name":"MBAUMUKU","Latitude":"","Longitude":"","Postal":"86511"},{"Code":"5313110008","Parent":"5313110","Name":"KAROT","Latitude":"","Longitude":"","Postal":"86512"},{"Code":"5313110009","Parent":"5313110","Name":"PITAK","Latitude":"","Longitude":"","Postal":"86513"},{"Code":"5313110010","Parent":"5313110","Name":"LAWIR","Latitude":"","Longitude":"","Postal":"86516"},{"Code":"5313110011","Parent":"5313110","Name":"WALI","Latitude":"","Longitude":"","Postal":"86514"},{"Code":"5313110012","Parent":"5313110","Name":"BANGKA LEDA","Latitude":"","Longitude":"","Postal":"86515"},{"Code":"5313110013","Parent":"5313110","Name":"ROWANG","Latitude":"","Longitude":"","Postal":"86517"},{"Code":"5313110014","Parent":"5313110","Name":"BANGKA NEKANG","Latitude":"","Longitude":"","Postal":"86511"},{"Code":"5313110015","Parent":"5313110","Name":"POCO MAL","Latitude":"","Longitude":"","Postal":"86518"},{"Code":"5313110016","Parent":"5313110","Name":"SATAR TACIK","Latitude":"","Longitude":"","Postal":"86518"},{"Code":"5313110017","Parent":"5313110","Name":"LACI CAREP","Latitude":"","Longitude":"","Postal":"86519"},{"Code":"5313110018","Parent":"5313110","Name":"COMPANG CAREP","Latitude":"","Longitude":"","Postal":"86519"},{"Code":"5313110019","Parent":"5313110","Name":"TADONG","Latitude":"","Longitude":"","Postal":"86512"},{"Code":"5313110020","Parent":"5313110","Name":"COMPANG TUKE","Latitude":"","Longitude":"","Postal":"86514"}]