[{"Code":"6108060001","Parent":"6108060","Name":"NANGA MANDAY","Latitude":"","Longitude":"","Postal":"78751,78753"},{"Code":"6108060004","Parent":"6108060","Name":"JELEMUK","Latitude":"","Longitude":"","Postal":"78751,78753"},{"Code":"6108060005","Parent":"6108060","Name":"BIKA","Latitude":"","Longitude":"","Postal":"78751,78753"},{"Code":"6108060006","Parent":"6108060","Name":"TELUK SINDUR","Latitude":"","Longitude":"","Postal":"78751,78753"},{"Code":"6108060008","Parent":"6108060","Name":"PENYELUANG","Latitude":"","Longitude":"","Postal":"78751,78753"},{"Code":"6108060011","Parent":"6108060","Name":"JONGKONG MANDAY","Latitude":"","Longitude":"","Postal":"78751,78753"},{"Code":"6108060012","Parent":"6108060","Name":"MELAPI MANDAY","Latitude":"","Longitude":"","Postal":"78751,78753"},{"Code":"6108060013","Parent":"6108060","Name":"BIKA HULU","Latitude":"","Longitude":"","Postal":"78751,78753"}]