[{"Code":"6213030001","Parent":"6213030","Name":"BATU TUHUP","Latitude":"","Longitude":"","Postal":"73992"},{"Code":"6213030002","Parent":"6213030","Name":"TUMBANG BAHAN","Latitude":"","Longitude":"","Postal":"73991,73992"},{"Code":"6213030003","Parent":"6213030","Name":"MUARA LAUNG I","Latitude":"","Longitude":"","Postal":"73991,73992"},{"Code":"6213030004","Parent":"6213030","Name":"MUARA LAUNG II","Latitude":"","Longitude":"","Postal":"73991,73992"},{"Code":"6213030005","Parent":"6213030","Name":"BERAS BELANGE","Latitude":"","Longitude":"","Postal":"73992"},{"Code":"6213030006","Parent":"6213030","Name":"MUARA TUHUP","Latitude":"","Longitude":"","Postal":"73991,73992"},{"Code":"6213030011","Parent":"6213030","Name":"BIHA","Latitude":"","Longitude":"","Postal":"73991,73992"},{"Code":"6213030012","Parent":"6213030","Name":"DIRUNG PUNDU","Latitude":"","Longitude":"","Postal":"73991,73992"},{"Code":"6213030013","Parent":"6213030","Name":"PELACI","Latitude":"","Longitude":"","Postal":"73991,73992"},{"Code":"6213030016","Parent":"6213030","Name":"DIRUNG PINANG","Latitude":"","Longitude":"","Postal":"73991,73992"},{"Code":"6213030017","Parent":"6213030","Name":"MUARA TUPUH","Latitude":"","Longitude":"","Postal":"73991,73992"},{"Code":"6213030022","Parent":"6213030","Name":"TAWAI HAUI","Latitude":"","Longitude":"","Postal":"73991,73992"},{"Code":"6213030023","Parent":"6213030","Name":"LAKUTAN","Latitude":"","Longitude":"","Postal":"73991,73992"},{"Code":"6213030024","Parent":"6213030","Name":"TUMBANG BANA","Latitude":"","Longitude":"","Postal":"73991,73992"},{"Code":"6213030025","Parent":"6213030","Name":"NARUI","Latitude":"","Longitude":"","Postal":"73991,73992"},{"Code":"6213030026","Parent":"6213030","Name":"MUARA MARUWEI I","Latitude":"","Longitude":"","Postal":"73991,73992"},{"Code":"6213030027","Parent":"6213030","Name":"MUARA MARUWEI II","Latitude":"","Longitude":"","Postal":"73991,73992"},{"Code":"6213030028","Parent":"6213030","Name":"PENDA SIRON","Latitude":"","Longitude":"","Postal":"73991,73992"},{"Code":"6213030029","Parent":"6213030","Name":"BATU BUA II","Latitude":"","Longitude":"","Postal":"73991,73992"},{"Code":"6213030030","Parent":"6213030","Name":"BATU BUA I","Latitude":"","Longitude":"","Postal":"73991,73992"},{"Code":"6213030031","Parent":"6213030","Name":"TAHUJAN LAUNG","Latitude":"","Longitude":"","Postal":"73991,73992"},{"Code":"6213030032","Parent":"6213030","Name":"KALANG DUHUNG","Latitude":"","Longitude":"","Postal":"73992"},{"Code":"6213030033","Parent":"6213030","Name":"BERALANG","Latitude":"","Longitude":"","Postal":"73992"},{"Code":"6213030034","Parent":"6213030","Name":"TUMBANG BONDANG","Latitude":"","Longitude":"","Postal":"73991,73992"},{"Code":"6213030035","Parent":"6213030","Name":"TUMBANG TONDUK","Latitude":"","Longitude":"","Postal":"73992"},{"Code":"6213030036","Parent":"6213030","Name":"BATU KARANG","Latitude":"","Longitude":"","Postal":"73991,73992"}]