[{"Code":"7204050001","Parent":"7204050","Name":"BETANIA","Latitude":"","Longitude":"","Postal":"94652"},{"Code":"7204050002","Parent":"7204050","Name":"TOINI","Latitude":"","Longitude":"","Postal":"94652"},{"Code":"7204050003","Parent":"7204050","Name":"MAPANE","Latitude":"","Longitude":"","Postal":"94652"},{"Code":"7204050004","Parent":"7204050","Name":"BEGA","Latitude":"","Longitude":"","Postal":"94652"},{"Code":"7204050005","Parent":"7204050","Name":"KASIGUNCU","Latitude":"","Longitude":"","Postal":"94652"},{"Code":"7204050006","Parent":"7204050","Name":"MASAMBA","Latitude":"","Longitude":"","Postal":"94652"},{"Code":"7204050007","Parent":"7204050","Name":"SAATU","Latitude":"","Longitude":"","Postal":"94652"},{"Code":"7204050008","Parent":"7204050","Name":"PINEDAPA","Latitude":"","Longitude":"","Postal":"94652"},{"Code":"7204050009","Parent":"7204050","Name":"MASANI","Latitude":"","Longitude":"","Postal":"94652"},{"Code":"7204050010","Parent":"7204050","Name":"TOKORONDO","Latitude":"","Longitude":"","Postal":"94652"},{"Code":"7204050011","Parent":"7204050","Name":"TIWAA","Latitude":"","Longitude":"","Postal":"94652"},{"Code":"7204050012","Parent":"7204050","Name":"LANTO JAYA","Latitude":"","Longitude":"","Postal":"94652"},{"Code":"7204050013","Parent":"7204050","Name":"LAPE","Latitude":"","Longitude":"","Postal":"94652"},{"Code":"7204050014","Parent":"7204050","Name":"TOWU","Latitude":"","Longitude":"","Postal":"94652"},{"Code":"7204050015","Parent":"7204050","Name":"TABALU","Latitude":"","Longitude":"","Postal":"94652"},{"Code":"7204050016","Parent":"7204050","Name":"UERALULU","Latitude":"","Longitude":"","Postal":"94652"}]