[{"Code":"7315020007","Parent":"7315020","Name":"MASSULOWALIE","Latitude":"","Longitude":"","Postal":"91261"},{"Code":"7315020009","Parent":"7315020","Name":"LANGNGA","Latitude":"","Longitude":"","Postal":"91261,91263"},{"Code":"7315020010","Parent":"7315020","Name":"PALLAMEANG","Latitude":"","Longitude":"","Postal":"91261"},{"Code":"7315020011","Parent":"7315020","Name":"MATTOMBONG","Latitude":"","Longitude":"","Postal":"91261"},{"Code":"7315020012","Parent":"7315020","Name":"PATOBONG","Latitude":"","Longitude":"","Postal":"91261"},{"Code":"7315020013","Parent":"7315020","Name":"SAMAENRE","Latitude":"","Longitude":"","Postal":"91261"},{"Code":"7315020014","Parent":"7315020","Name":"MATTONGANG TONGANG","Latitude":"","Longitude":"","Postal":"91261"},{"Code":"7315020015","Parent":"7315020","Name":"MATTIRO TASI","Latitude":"","Longitude":"","Postal":"91261"},{"Code":"7315020016","Parent":"7315020","Name":"SIWOLONG POLONG","Latitude":"","Longitude":"","Postal":"91261"}]