[{"Code":"7403100010","Parent":"7403100","Name":"BAINI","Latitude":"","Longitude":"","Postal":"93458"},{"Code":"7403100011","Parent":"7403100","Name":"KONGGA MEA","Latitude":"","Longitude":"","Postal":"93475,93458"},{"Code":"7403100012","Parent":"7403100","Name":"POHARA","Latitude":"","Longitude":"","Postal":"93475,93458"},{"Code":"7403100013","Parent":"7403100","Name":"ANDEPALI","Latitude":"","Longitude":"","Postal":"93475,93458"},{"Code":"7403100014","Parent":"7403100","Name":"WAWOLIMBUE","Latitude":"","Longitude":"","Postal":"93475,93458"},{"Code":"7403100015","Parent":"7403100","Name":"SAMPARA","Latitude":"","Longitude":"","Postal":"93475,93458"},{"Code":"7403100016","Parent":"7403100","Name":"ANDADOWI","Latitude":"","Longitude":"","Postal":"93475,93458"},{"Code":"7403100017","Parent":"7403100","Name":"POLUA","Latitude":"","Longitude":"","Postal":"93475,93458"},{"Code":"7403100018","Parent":"7403100","Name":"RAWUA","Latitude":"","Longitude":"","Postal":"93475,93458"},{"Code":"7403100019","Parent":"7403100","Name":"BAO-BAO","Latitude":"","Longitude":"","Postal":"93458"},{"Code":"7403100020","Parent":"7403100","Name":"PUULORO","Latitude":"","Longitude":"","Postal":"93475,93458"},{"Code":"7403100021","Parent":"7403100","Name":"BONDOALA","Latitude":"","Longitude":"","Postal":"93475,93458"},{"Code":"7403100022","Parent":"7403100","Name":"ANDAROA","Latitude":"","Longitude":"","Postal":"93475,93458"},{"Code":"7403100023","Parent":"7403100","Name":"TOTOMBE JAYA","Latitude":"","Longitude":"","Postal":"93475,93458"}]