[{"Code":"8101042003","Parent":"8101042","Name":"BATU PUTIH","Latitude":"","Longitude":"","Postal":"97471,97472"},{"Code":"8101042004","Parent":"8101042","Name":"WERMATANG","Latitude":"","Longitude":"","Postal":"97471,97472"},{"Code":"8101042005","Parent":"8101042","Name":"MAKATIAN","Latitude":"","Longitude":"","Postal":"97471,97472"},{"Code":"8101042006","Parent":"8101042","Name":"WERATAN","Latitude":"","Longitude":"","Postal":"97471,97472"},{"Code":"8101042007","Parent":"8101042","Name":"THEMIN","Latitude":"","Longitude":"","Postal":"97471,97472"},{"Code":"8101042008","Parent":"8101042","Name":"WELUTU","Latitude":"","Longitude":"","Postal":"97471,97472"},{"Code":"8101042009","Parent":"8101042","Name":"RUMAH SALUT","Latitude":"","Longitude":"","Postal":"97471,97472"},{"Code":"8101042010","Parent":"8101042","Name":"KAMATUBUN","Latitude":"","Longitude":"","Postal":"97472"},{"Code":"8101042011","Parent":"8101042","Name":"MARANTUTUL","Latitude":"","Longitude":"","Postal":"97471,97472"}]