[{"Code":"9402193005","Parent":"9402193","Name":"MULIMA","Latitude":"","Longitude":"","Postal":"99522"},{"Code":"9402193006","Parent":"9402193","Name":"WENABUBAGA","Latitude":"","Longitude":"","Postal":"99522"},{"Code":"9402193024","Parent":"9402193","Name":"KILUBAGA","Latitude":"","Longitude":"","Postal":"99522"},{"Code":"9402193025","Parent":"9402193","Name":"MUSALFAK","Latitude":"","Longitude":"","Postal":"99522"},{"Code":"9402193026","Parent":"9402193","Name":"PUNAKUL","Latitude":"","Longitude":"","Postal":"99522"}]