[{"Code":"9409040001","Parent":"9409040","Name":"SAREIDI","Latitude":"","Longitude":"","Postal":"98541"},{"Code":"9409040002","Parent":"9409040","Name":"OWI","Latitude":"","Longitude":"","Postal":"98541"},{"Code":"9409040003","Parent":"9409040","Name":"RIM","Latitude":"","Longitude":"","Postal":"98541"},{"Code":"9409040004","Parent":"9409040","Name":"YENUSI","Latitude":"","Longitude":"","Postal":"98541"},{"Code":"9409040005","Parent":"9409040","Name":"ORWER","Latitude":"","Longitude":"","Postal":"98541"},{"Code":"9409040006","Parent":"9409040","Name":"WONIKI","Latitude":"","Longitude":"","Postal":"98541"},{"Code":"9409040007","Parent":"9409040","Name":"BINDUSI","Latitude":"","Longitude":"","Postal":"98541"},{"Code":"9409040008","Parent":"9409040","Name":"KAJASI","Latitude":"","Longitude":"","Postal":"98541"},{"Code":"9409040009","Parent":"9409040","Name":"KAJASBO","Latitude":"","Longitude":"","Postal":"98541"},{"Code":"9409040017","Parent":"9409040","Name":"RIMBA JAYA","Latitude":"","Longitude":"","Postal":"98541"},{"Code":"9409040018","Parent":"9409040","Name":"SOON","Latitude":"","Longitude":"","Postal":"98541"},{"Code":"9409040019","Parent":"9409040","Name":"SUNDE","Latitude":"","Longitude":"","Postal":"98541"},{"Code":"9409040020","Parent":"9409040","Name":"SEPSE","Latitude":"","Longitude":"","Postal":"98541"},{"Code":"9409040021","Parent":"9409040","Name":"RUAR","Latitude":"","Longitude":"","Postal":"98541"},{"Code":"9409040022","Parent":"9409040","Name":"MANDON","Latitude":"","Longitude":"","Postal":"98541"},{"Code":"9409040023","Parent":"9409040","Name":"INSUMARIRES","Latitude":"","Longitude":"","Postal":"98541"},{"Code":"9409040024","Parent":"9409040","Name":"SORYAR","Latitude":"","Longitude":"","Postal":"98541"},{"Code":"9409040025","Parent":"9409040","Name":"YENDAKEM","Latitude":"","Longitude":"","Postal":"98541"},{"Code":"9409040026","Parent":"9409040","Name":"WASORI","Latitude":"","Longitude":"","Postal":"98541"},{"Code":"9409040027","Parent":"9409040","Name":"AFEFBO","Latitude":"","Longitude":"","Postal":"98541"},{"Code":"9409040028","Parent":"9409040","Name":"YENBEROK","Latitude":"","Longitude":"","Postal":"98541"},{"Code":"9409040029","Parent":"9409040","Name":"ADORBARI","Latitude":"","Longitude":"","Postal":"98541"},{"Code":"9409040030","Parent":"9409040","Name":"BOSNIK SUP","Latitude":"","Longitude":"","Postal":"98541"},{"Code":"9409040031","Parent":"9409040","Name":"INOFI","Latitude":"","Longitude":"","Postal":"98541"},{"Code":"9409040032","Parent":"9409040","Name":"WADERBO","Latitude":"","Longitude":"","Postal":"98541"},{"Code":"9409040033","Parent":"9409040","Name":"INMDI","Latitude":"","Longitude":"","Postal":"98541"}]