[{"Code":"9417011001","Parent":"9417011","Name":"TARANGOP","Latitude":"","Longitude":"","Postal":"99575,99433"},{"Code":"9417011002","Parent":"9417011","Name":"ARINTAP","Latitude":"","Longitude":"","Postal":"99575,99433"},{"Code":"9417011004","Parent":"9417011","Name":"SAKUP","Latitude":"","Longitude":"","Postal":"99575,99433"},{"Code":"9417011005","Parent":"9417011","Name":"NANUM","Latitude":"","Longitude":"","Postal":"99575,99433"},{"Code":"9417011006","Parent":"9417011","Name":"KAWOR","Latitude":"","Longitude":"","Postal":"99575,99433"},{"Code":"9417011007","Parent":"9417011","Name":"ATER","Latitude":"","Longitude":"","Postal":"99575,99433"},{"Code":"9417011008","Parent":"9417011","Name":"UMDING","Latitude":"","Longitude":"","Postal":"99575,99433"}]