[{"Code":"9418049001","Parent":"9418049","Name":"SEBEY","Latitude":"","Longitude":"","Postal":""},{"Code":"9418049002","Parent":"9418049","Name":"MABURUK","Latitude":"","Longitude":"","Postal":"99438"},{"Code":"9418049003","Parent":"9418049","Name":"DARE","Latitude":"","Longitude":"","Postal":""},{"Code":"9418049004","Parent":"9418049","Name":"ROGIA","Latitude":"","Longitude":"","Postal":""},{"Code":"9418049005","Parent":"9418049","Name":"SERIAU","Latitude":"","Longitude":"","Postal":""},{"Code":"9418049006","Parent":"9418049","Name":"IREGE","Latitude":"","Longitude":"","Postal":""},{"Code":"9418049007","Parent":"9418049","Name":"TUBY","Latitude":"","Longitude":"","Postal":""},{"Code":"9418049008","Parent":"9418049","Name":"KONDALA","Latitude":"","Longitude":"","Postal":""},{"Code":"9418049009","Parent":"9418049","Name":"YONIRA","Latitude":"","Longitude":"","Postal":"99437,99053"},{"Code":"9418049010","Parent":"9418049","Name":"TABONAKME","Latitude":"","Longitude":"","Postal":"99437,99053"}]