[{"Code":"9430060003","Parent":"9430060","Name":"BAGI","Latitude":"","Longitude":"","Postal":"99533,99589"},{"Code":"9430060004","Parent":"9430060","Name":"MALAGAI","Latitude":"","Longitude":"","Postal":"99533,99589"},{"Code":"9430060005","Parent":"9430060","Name":"OKA","Latitude":"","Longitude":"","Postal":"99533,99589"},{"Code":"9430060006","Parent":"9430060","Name":"NAMBU","Latitude":"","Longitude":"","Postal":"99589"},{"Code":"9430060007","Parent":"9430060","Name":"GANUME","Latitude":"","Longitude":"","Postal":"99589"},{"Code":"9430060008","Parent":"9430060","Name":"BINILANI","Latitude":"","Longitude":"","Postal":"99589"},{"Code":"9430060009","Parent":"9430060","Name":"GUMBAN","Latitude":"","Longitude":"","Postal":"99589"},{"Code":"9430060010","Parent":"9430060","Name":"LOWANOM","Latitude":"","Longitude":"","Postal":"99589"}]